setup.cfg
setup.py
mcu_info_util/__init__.py
mcu_info_util/__main__.py
mcu_info_util/device_tree.py
mcu_info_util/linker_script.py
mcu_info_util/svd_utils.py
mcu_info_util/toolchain.py
mcu_info_util/toolchain_arm.py
mcu_info_util/toolchain_avr.py
mcu_info_util/toolchain_msp430.py
mcu_info_util/utils.py
mcu_info_util.egg-info/PKG-INFO
mcu_info_util.egg-info/SOURCES.txt
mcu_info_util.egg-info/dependency_links.txt
mcu_info_util.egg-info/entry_points.txt
mcu_info_util.egg-info/requires.txt
mcu_info_util.egg-info/top_level.txt
mcu_info_util/data/devices.data